LICENSE
MANIFEST.in
README.md
setup.cfg
setup.py
r2diaphora/__init__.py
r2diaphora/diaphora.py
r2diaphora/diaphora_heuristics.py
r2diaphora/diaphora_r2.py
r2diaphora/difflibparser.py
r2diaphora/html_diff.py
r2diaphora.egg-info/PKG-INFO
r2diaphora.egg-info/SOURCES.txt
r2diaphora.egg-info/dependency_links.txt
r2diaphora.egg-info/entry_points.txt
r2diaphora.egg-info/requires.txt
r2diaphora.egg-info/top_level.txt
r2diaphora/idaapi/__init__.py
r2diaphora/idaapi/idaapi_to_r2.py
r2diaphora/idaapi/instructions.py
r2diaphora/jkutils/__init__.py
r2diaphora/jkutils/factor.py
r2diaphora/jkutils/graph_hashes.py
r2diaphora/jkutils/kfuzzy.py
r2diaphora/others/__init__.py
r2diaphora/others/tarjan_sort.py
scripts/r2diaphora-bulk
scripts/r2diaphora-db