Metadata-Version: 2.1
Name: r2diaphora
Version: 0.3.0
Summary: radare2 port of diaphora
Home-page: https://github.com/FernandoDoming/r2diaphora
Author: Fernando Domínguez
Author-email: fernando.dom.del@gmail.com
License: GNU GPL v3
Platform: UNKNOWN
Classifier: Programming Language :: Python :: 3.5
Classifier: Programming Language :: Python :: 3.6
Classifier: Programming Language :: Python :: 3.7
Classifier: Programming Language :: Python :: 3.8
Classifier: Programming Language :: Python :: 3.9
Classifier: Programming Language :: Python :: 3.10
License-File: LICENSE
